langchainhub/__init__.py
langchainhub/_types.py
langchainhub/client.py
langchainhub-0.1.19.dist-info/LICENSE
langchainhub-0.1.19.dist-info/METADATA
langchainhub-0.1.19.dist-info/WHEEL
langchainhub-0.1.19.dist-info/RECORD
