Metadata-Version: 2.1
Name: langchainhub
Version: 0.1.19
Summary: The LangChain Hub API client
License: MIT
Author: LangChain
Author-email: support@langchain.dev
Requires-Python: >=3.8.1,<4.0
Classifier: License :: OSI Approved :: MIT License
Classifier: Programming Language :: Python :: 3
Classifier: Programming Language :: Python :: 3.9
Classifier: Programming Language :: Python :: 3.10
Classifier: Programming Language :: Python :: 3.11
Classifier: Programming Language :: Python :: 3.12
Requires-Dist: packaging (>=24.1,<25.0)
Requires-Dist: requests (>=2,<3)
Requires-Dist: types-requests (>=2.31.0.2,<3.0.0.0)
